Metadata-Version: 2.1
Name: dcp-client
Version: 1.0
Summary: Client to authorize requests against the gen3 DCP
Home-page: https://github.com/david4096/dcp
Author: David Steinberg
Author-email: david@resium.com
License: Apache License 2.0
Platform: UNKNOWN
Classifier: Development Status :: 3 - Alpha
Classifier: Intended Audience :: Science/Research
Classifier: License :: OSI Approved :: Apache Software License
Classifier: Programming Language :: Python :: 2.7
Classifier: Programming Language :: Python :: 3.6
Classifier: Topic :: Scientific/Engineering :: Bio-Informatics
